{
    "A1配置说明": {
        "说明": "开启状态1代表开启，0代表关闭，怪物级别代表谣言：提示【SS级】怪物降世"
    },
    "boss1": {
        "等级": 139,
        "副怪名字": "天兵",
        "副怪图标": 6223,
        "附加法攻": 10000,
        "附加防御": 10000,
        "附加气血": 1000000,
        "附加速度": 3000,
        "附加物攻": 10000,
        "怪物道行": 365000,
        "怪物级别": "1阶天仙试炼",
        "开启状态": 1,
        "刷新间隔": 60,
        "刷新数量": 1,
        "挑战次数": 5,
        "主怪名字": "1阶哪吒",
        "主怪图标": 22009
    },
    "boss10": {
        "等级": 220,
        "副怪名字": "老祖门徒",
        "副怪图标": 6064,
        "附加法攻": 80000,
        "附加防御": 10000,
        "附加气血": 8500000,
        "附加速度": 8000,
        "附加物攻": 80000,
        "怪物道行": 7300000,
        "怪物级别": "10阶天仙试炼",
        "开启状态": 1,
        "刷新间隔": 180,
        "刷新数量": 1,
        "挑战次数": 5,
        "主怪名字": "10阶鸿鹄老祖",
        "主怪图标": 20065
    },
    "boss2": {
        "等级": 149,
        "副怪名字": "千年雷怪",
        "副怪图标": 6171,
        "附加法攻": 15000,
        "附加防御": 10000,
        "附加气血": 1500000,
        "附加速度": 3500,
        "附加物攻": 15000,
        "怪物道行": 730000,
        "怪物级别": "2阶天仙试炼",
        "开启状态": 1,
        "刷新间隔": 60,
        "刷新数量": 1,
        "挑战次数": 5,
        "主怪名字": "2阶雷震子",
        "主怪图标": 22010
    },
    "boss3": {
        "等级": 159,
        "副怪名字": "魔礼红",
        "副怪图标": 6243,
        "附加法攻": 20000,
        "附加防御": 10000,
        "附加气血": 2000000,
        "附加速度": 4000,
        "附加物攻": 20000,
        "怪物道行": 1095000,
        "怪物级别": "3阶天仙试炼",
        "开启状态": 1,
        "刷新间隔": 60,
        "刷新数量": 1,
        "挑战次数": 5,
        "主怪名字": "3阶托塔天王",
        "主怪图标": 22008
    },
    "boss4": {
        "等级": 169,
        "副怪名字": "哮天犬",
        "副怪图标": 22007,
        "附加法攻": 25000,
        "附加防御": 10000,
        "附加气血": 2500000,
        "附加速度": 4500,
        "附加物攻": 25000,
        "怪物道行": 1460000,
        "怪物级别": "4阶天仙试炼",
        "开启状态": 1,
        "刷新间隔": 60,
        "刷新数量": 1,
        "挑战次数": 5,
        "主怪名字": "4阶二郎神",
        "主怪图标": 22006
    },
    "boss5": {
        "等级": 175,
        "副怪名字": "炼丹童子",
        "副怪图标": 20075,
        "附加法攻": 30000,
        "附加防御": 10000,
        "附加气血": 3000000,
        "附加速度": 5000,
        "附加物攻": 30000,
        "怪物道行": 1825000,
        "怪物级别": "5阶天仙试炼",
        "开启状态": 1,
        "刷新间隔": 60,
        "刷新数量": 1,
        "挑战次数": 5,
        "主怪名字": "5阶太上老君",
        "主怪图标": 22005
    },
    "boss6": {
        "等级": 180,
        "副怪名字": "天君随从",
        "副怪图标": 21023,
        "附加法攻": 35000,
        "附加防御": 10000,
        "附加气血": 3500000,
        "附加速度": 5500,
        "附加物攻": 35000,
        "怪物道行": 2190000,
        "怪物级别": "6阶天仙试炼",
        "开启状态": 1,
        "刷新间隔": 60,
        "刷新数量": 1,
        "挑战次数": 5,
        "主怪名字": "6阶朱天君",
        "主怪图标": 20063
    },
    "boss7": {
        "等级": 185,
        "副怪名字": "斗战胜佛",
        "副怪图标": 22017,
        "附加法攻": 45000,
        "附加防御": 10000,
        "附加气血": 4000000,
        "附加速度": 6000,
        "附加物攻": 45000,
        "怪物道行": 2555000,
        "怪物级别": "7阶天仙试炼",
        "开启状态": 1,
        "刷新间隔": 60,
        "刷新数量": 1,
        "挑战次数": 5,
        "主怪名字": "7阶弼马温",
        "主怪图标": 6417
    },
    "boss8": {
        "等级": 190,
        "副怪名字": "随从仙子",
        "副怪图标": 22004,
        "附加法攻": 50000,
        "附加防御": 10000,
        "附加气血": 4500000,
        "附加速度": 6500,
        "附加物攻": 50000,
        "怪物道行": 2920000,
        "怪物级别": "8阶天仙试炼",
        "开启状态": 1,
        "刷新间隔": 60,
        "刷新数量": 1,
        "挑战次数": 5,
        "主怪名字": "8阶王母娘娘",
        "主怪图标": 22002
    },
    "boss9": {
        "等级": 200,
        "副怪名字": "二郎神",
        "副怪图标": 22006,
        "附加法攻": 55000,
        "附加防御": 10000,
        "附加气血": 4500000,
        "附加速度": 7000,
        "附加物攻": 55000,
        "怪物道行": 3650000,
        "怪物级别": "9阶天仙试炼",
        "开启状态": 0,
        "刷新间隔": 60,
        "刷新数量": 1,
        "挑战次数": 5,
        "主怪名字": "9阶玉皇大帝",
        "主怪图标": 22001
    }
}