{
    "夫诸": {
        "需要数量": 100
    },
    "降魔": {
        "需要数量": 150
    },
    "震魃": {
        "需要数量": 200
    },
    "赤天": {
        "需要数量": 250
    },
    "混沌": {
        "需要数量": 300
    },
    "笛舞": {
        "需要数量": 350
    },	
    "齐天大圣": {
        "需要数量": 400
    },
    "涡斗": {
        "需要数量": 450
    },
    "逐鹿": {
        "需要数量": 550
    },
    "巨力": {
        "需要数量": 600
    },		
    "苍穹": {
        "需要数量": 650
    },
    "净瓶": {
        "需要数量": 700
    },
    "无名": {
        "需要数量": 800
    },

    "写个鸡儿": {
        "写个鸡儿": "写个鸡儿",
        "写个鸡儿": "写个鸡儿"
    }
}