{
    "七日礼包": {
        "1": "#I宠物|无极熊(精怪)#r1#I#I首饰|80级X5首饰#r1#I#I金钱|金钱#r1000#I",
        "2": "#I首饰|60级首饰#r1#I#I物品|超级仙风散#r10#I#I物品|宠物强化丹#r20#I",
        "3": "#I物品|超级仙风散#r10#I#I物品|宠物强化丹#r20#I#I物品|超级藏宝图#r10#I",
        "4": "#I物品|超级仙风散#r10#I#I物品|召唤令・十二生肖#r20#I#I物品|超级藏宝图#r10#I",
        "5": "#I物品|超级仙风散#r10#I#I物品|召唤令・十二生肖#r20#I#I物品|超级藏宝图#r10#I",
        "6": "#I物品|改头换面卡#r1#I#I物品|超级仙风散#r10#I#I物品|召唤令・十二生肖#r20#I",
        "7": "#I物品|冥海霞光#r10#I#I物品|超级仙风散#r10#I#I物品|召唤令・十二生肖#r20#I#I"
    },
    "每日签到": {
        "1": "银元宝|50000",
        "9": "银元宝|50000",
        "2": "召唤令・十二生肖|5",
        "3": "银元宝|50000",
        "4": "召唤令・十二生肖|5",
        "5": "银元宝|50000",
        "6": "召唤令・十二生肖|5",
        "30": "召唤令・十二生肖|10",
        "7": "召唤令・上古神兽|5",
        "8": "召唤令・十二生肖|5",
        "10": "召唤令・十二生肖|5",
        "29": "召唤令・上古神兽|5",
        "11": "银元宝|50000",
        "28": "召唤令・十二生肖|10",
        "12": "召唤令・十二生肖|5",
        "13": "银元宝|50000",
        "14": "召唤令・上古神兽|5",
        "15": "召唤令・十二生肖|5",
        "16": "银元宝|50000",
        "17": "召唤令・十二生肖|5",
        "18": "银元宝|50000",
        "21": "召唤令・上古神兽|5",
        "19": "召唤令・十二生肖|10",
        "20": "银元宝|50000",
        "22": "召唤令・十二生肖|10",
        "23": "银元宝|50000",
        "24": "召唤令・十二生肖|10",
        "25": "银元宝|50000",
        "26": "召唤令・十二生肖|10",
        "27": "银元宝|50000"
    }
}